cubicweb_fckeditorcompat/__init__.py
cubicweb_fckeditorcompat/__pkginfo__.py
cubicweb_fckeditorcompat/views.py
cubicweb_fckeditorcompat/data/fckeditor/fckconfig.js
cubicweb_fckeditorcompat/data/fckeditor/fckeditor.afp
cubicweb_fckeditorcompat/data/fckeditor/fckeditor.asp
cubicweb_fckeditorcompat/data/fckeditor/fckeditor.cfc
cubicweb_fckeditorcompat/data/fckeditor/fckeditor.cfm
cubicweb_fckeditorcompat/data/fckeditor/fckeditor.js
cubicweb_fckeditorcompat/data/fckeditor/fckeditor.lasso
cubicweb_fckeditorcompat/data/fckeditor/fckeditor.php
cubicweb_fckeditorcompat/data/fckeditor/fckeditor.pl
cubicweb_fckeditorcompat/data/fckeditor/fckeditor.py
cubicweb_fckeditorcompat/data/fckeditor/fckeditor_php4.php
cubicweb_fckeditorcompat/data/fckeditor/fckeditor_php5.php
cubicweb_fckeditorcompat/data/fckeditor/fckpackager.xml
cubicweb_fckeditorcompat/data/fckeditor/fckstyles.xml
cubicweb_fckeditorcompat/data/fckeditor/fcktemplates.xml
cubicweb_fckeditorcompat/data/fckeditor/fckutils.cfm
cubicweb_fckeditorcompat/data/fckeditor/editor/fckdebug.html
cubicweb_fckeditorcompat/data/fckeditor/editor/fckdialog.html
cubicweb_fckeditorcompat/data/fckeditor/editor/fckeditor.html
cubicweb_fckeditorcompat/data/fckeditor/editor/fckeditor.original.html
cubicweb_fckeditorcompat/data/fckeditor/editor/_source/fckconstants.js
cubicweb_fckeditorcompat/data/fckeditor/editor/_source/fckeditorapi.js
cubicweb_fckeditorcompat/data/fckeditor/editor/_source/fckjscoreextensions.js
cubicweb_fckeditorcompat/data/fckeditor/editor/_source/fckscriptloader.js
cubicweb_fckeditorcompat/data/fckeditor/editor/_source/classes/fckcontextmenu.js
cubicweb_fckeditorcompat/data/fckeditor/editor/_source/classes/fckdataprocessor.js
cubicweb_fckeditorcompat/data/fckeditor/editor/_source/classes/fckdocumentfragment_gecko.js
cubicweb_fckeditorcompat/data/fckeditor/editor/_source/classes/fckdocumentfragment_ie.js
cubicweb_fckeditorcompat/data/fckeditor/editor/_source/classes/fckdomrange.js
cubicweb_fckeditorcompat-0.5.0.dist-info/METADATA
cubicweb_fckeditorcompat-0.5.0.dist-info/WHEEL
cubicweb_fckeditorcompat-0.5.0.dist-info/entry_points.txt
cubicweb_fckeditorcompat-0.5.0.dist-info/top_level.txt
cubicweb_fckeditorcompat-0.5.0.dist-info/RECORD
