Metadata-Version: 2.1
Name: cubicweb-fckeditorcompat
Version: 0.5.0
Summary: contains fckeditor 1:2.6.6-3 code
Home-page: https://forge.extranet.logilab.fr/cubicweb/cubes/cubicweb-fckeditorcompat
Author: LOGILAB S.A. (Paris, FRANCE)
Author-email: contact@logilab.fr
License: LGPL
Platform: UNKNOWN
Classifier: Environment :: Web Environment
Classifier: Framework :: CubicWeb
Classifier: Programming Language :: Python
Classifier: Programming Language :: JavaScript
Requires-Dist: cubicweb (<3.33.0,>=3.24.0)
